sifflet_mcp/__init__.py
sifflet_mcp/server.py
sifflet_mcp-0.1.6.dist-info/METADATA
sifflet_mcp-0.1.6.dist-info/WHEEL
sifflet_mcp-0.1.6.dist-info/entry_points.txt
sifflet_mcp-0.1.6.dist-info/licenses/LICENSE
sifflet_mcp-0.1.6.dist-info/RECORD
