Metadata-Version: 2.4
Name: sifflet-mcp
Version: 0.1.6
Summary: MCP server for interaction with Sifflet data observability platform
Author-email: Baptiste Azéma <baptiste@siffletdata.com>, Marie Berard <marie@siffletdata.com>, Pierre Courgeon <pierre.courgeon@siffletdata.com>
License-File: LICENSE
Requires-Python: >=3.13
Requires-Dist: mcp>=1.8.1
Requires-Dist: python-dotenv>=1.1.0
Requires-Dist: sifflet-sdk>=0.3.22
